csv_to_sqlite/__init__.py
csv_to_sqlite/core.py
csv_to_sqlite/gui.py
ulg_csvtosqlite-1.0.0.dist-info/LICENSE
ulg_csvtosqlite-1.0.0.dist-info/METADATA
ulg_csvtosqlite-1.0.0.dist-info/WHEEL
ulg_csvtosqlite-1.0.0.dist-info/entry_points.txt
ulg_csvtosqlite-1.0.0.dist-info/top_level.txt
ulg_csvtosqlite-1.0.0.dist-info/RECORD
