Metadata-Version: 2.1
Name: ulg-csvtosqlite
Version: 1.0.0
Summary: A library for importing CSV files into SQLite databases with optional GUI support
Home-page: https://github.com/mmpdfcollection/ulg-csv-to-sqlite
Author: MMPDF Collection
Author-email: mmpdfcollection@gmail.com
License: MIT
Classifier: Programming Language :: Python :: 3
Classifier: License :: OSI Approved :: MIT License
Classifier: Operating System :: OS Independent
License-File: LICENSE
Provides-Extra: gui
Requires-Dist: tkinter; extra == "gui"
